{
    "bjcp": "3A",
    "id": "6804",
    "ingredients": [
        "9 lbs 8.0 oz - Pale Malt (2 Row) US (2.0 SRM) (Grain)",
        "8.0 oz - Caravienne Malt (22.0 SRM) (Grain)",
        "4.0 oz - Caramel/Crystal Malt - 10L (10.0 SRM) (Grain)",
        "4.0 oz - Cara-Pils/Dextrine (2.0 SRM) (Grain)",
        "1.0 oz - Perle [7.4%] - Boil 60 min (Hops)",
        "1.0 oz - Cascade [5.5%] - Steep 10 min (Hops)",
        "0 pkgs - American Ale (Wyeast Labs #1056) (Yeast)"
    ],
    "name": "Beach Party Blonde",
    "name_raw": "Beach Party Blonde",
    "rating": "3.0",
    "source": "beerrecipes.com",
    "style": "Vienna Lager",
    "style_raw": "Vienna Lager",
    "votes": "1"
}