{
    "bjcp": "2C",
    "id": "11861",
    "ingredients": [
        "1 lbs - Pale Ale (2-row) (3.0 SRM) (Grain)",
        "8.0 oz - Rye Malt (Briess) (3.7 SRM) (Grain)",
        "2.0 oz - Pale Malt, Golden Promise (Thomas Fawcett) (3.0 SRM) (Grain)",
        "1.5 oz - Caramel Malt - 60L (Briess) (60.0 SRM) (Grain)",
        "1.0 oz - Caramel/Crystal Malt - 40L (40.0 SRM) (Grain)",
        "0.5 oz - Caramel Malt - 120L (Briess) (120.0 SRM) (Grain)",
        "0.2 oz - Chocolate Malt (350.0 SRM) (Grain)",
        "0.2 oz - De-Bittered Black Malt (Dingemans) (550.0 SRM) (Grain)",
        "7.0 oz - Sugar, Table (Sucrose) (1.0 SRM) (Grain)",
        "2.0 oz - Tettnang (Tettnang Tettnager) [3.9%] - Boil 60 min (Hops)",
        "4 lbs 8.0 oz - LME Pilsen Light (Briess) [Boil for 50 min] (2.3 SRM) (Grain)",
        "1.00 - Whirlfloc Tablet (Boil 15 min) (Misc)",
        "2.0 oz - Tettnang (Tettnang Tettnager) [3.9%] - Boil 15 min (Hops)",
        "1.00 tsp - Yeast Nutrient (Boil 10 min) (Misc)",
        "2 pkgs - Czech Pilsner Lager (Wyeast Labs #2278) (Yeast)"
    ],
    "name": "Partigyle Rye Pilsner PM",
    "name_raw": "Partigyle Rye Pilsner PM",
    "rating": 2,
    "source": "beerrecipes.com",
    "style": "Classic American Pilsner",
    "style_raw": "Classic American Pilsner",
    "votes": 0
}