{
    "bjcp": "20A",
    "id": "581",
    "ingredients": [
        "5 pounds, pale malt extract syrup",
        "1 pound, corn sugar",
        "2 ounces, Hallertauer hops (boil)",
        "1/2 ounce, Hallertauer hops (finish)",
        "6 pounds, cranberries",
        "ale yeast",
        "corn sugar (priming)"
    ],
    "name": "Cranbeery Ale",
    "name_raw": "Cranbeery Ale",
    "rating": "3.9",
    "source": "beerrecipes.com",
    "style": "Fruit Beer",
    "style_raw": "Fruit Beer",
    "votes": "11"
}