{
    "bjcp": "13C",
    "id": "13582",
    "ingredients": [
        "12.0 oz - Victory Malt (25.0 SRM) (Grain)",
        "15.9 oz - Oats, Flaked (1.0 SRM) (Grain)",
        "9 lbs 7.7 oz - Pale Malt, Maris Otter (3.0 SRM) (Grain)",
        "8.0 oz - Caramel/Crystal Malt - 80L (80.0 SRM) (Grain)",
        "12.0 oz - Chocolate Malt (350.0 SRM) (Grain)",
        "8.0 oz - Black Barley (Stout) (500.0 SRM) (Grain)",
        "1.8 oz - Goldings, East Kent [4.3%] - Boil 60 min (Hops)",
        "0.50 - Whirlfloc Tablet (Boil 15 min) (Misc)",
        "1.00 tsp - Yeast Nutrient (Boil 10 min) (Misc)",
        "1.00 - coffee espresso shot (Boil 10 min) (Misc)",
        "1 pkgs - SafAle English Ale (DCL/Fermentis #S-04) (Yeast)"
    ],
    "name": "Oatmeal Stout (BIAB) &quot;Breakfast Stout&quot;",
    "name_raw": "Oatmeal Stout (BIAB) &quot;Breakfast Stout&quot;",
    "rating": "5.0",
    "source": "beerrecipes.com",
    "style": "Oatmeal Stout",
    "style_raw": "Oatmeal Stout",
    "votes": "1"
}