{
    "bjcp": "23A",
    "id": "13837",
    "ingredients": [
        "15 lbs Pilsner malt (1.7 srm)",
        "1 lb Carapils (1.5 srm)",
        "4 oz Munich 10L (10 srm)",
        "1 oz Centennial hops for bittering &ndash; boil 60 minutes",
        "1 oz Hallertau &ndash; boil one minute",
        "1 oz Saaz &ndash; steeped",
        "2 Packets 1007 German ale yeast"
    ],
    "name": "Mickey J - Double Pilsner Ale",
    "name_raw": "Mickey J - Double Pilsner Ale",
    "rating": "5.0",
    "source": "beerrecipes.com",
    "style": "Specialty Beer",
    "style_raw": "Specialty Beer",
    "votes": "1"
}