{
    "bjcp": "14C",
    "id": "12196",
    "ingredients": [
        "11.25 g - .Gypsum (Calcium Sulfate) (Mash 60 min) (Misc)",
        "30 lbs 13.8 oz - Pale Ale (2.8 SRM) (Grain)",
        "2 lbs 3.3 oz - Bursztynowy (15.2 SRM) (Grain)",
        "1 lbs 1.6 oz - Pszeniczny (1.5 SRM) (Grain)",
        "2 lbs 3.3 oz - Sugar, Table (Sucrose) (1.0 SRM) (Grain)",
        "2.5 oz - Magnum [12.0%] - Boil 90 min (Hops)",
        "1.2 oz - Mosaic (HBC 369) [12.2%] - Boil 60 min (Hops)",
        "1.2 oz - Simcoe [13.0%] - Boil 30 min (Hops)",
        "1.2 oz - Citra [12.0%] - Boil 10 min (Hops)",
        "0.7 oz - Simcoe [13.0%] - Boil 5 min (Hops)",
        "1 pkgs - Safale American (DCL/Fermentis #US-05) (Yeast)",
        "1.4 oz - Citra [12.0%] - Dry Hop 7 days (Hops)"
    ],
    "name": "Fruit Double IPA",
    "name_raw": "Fruit Double IPA",
    "rating": 2,
    "source": "beerrecipes.com",
    "style": "Imperial IPA",
    "style_raw": "Imperial IPA",
    "votes": 0
}