{
    "bjcp": "7B",
    "id": "285",
    "ingredients": [
        "8 pounds, Klages malt",
        "1 pound, light munich malt",
        "1/2 pound, 10L Crystal malt",
        "1/4 pound, 40L Crystal",
        "1/4 pound, 80L Crystal",
        "2 ounces, Northern Brewer Hops (Whole) (7.5% a)",
        "1 tablespoon, Irish Moss",
        "Wyeast #2112 California Lager yeast in 1/2 gallon starter"
    ],
    "name": "Southside Steam Beer",
    "name_raw": "Southside Steam Beer",
    "rating": "4.1",
    "source": "beerrecipes.com",
    "style": "California Common Beer",
    "style_raw": "California Common Beer",
    "votes": "11"
}