{
    "bjcp": "13B",
    "id": "2997",
    "ingredients": [
        "12.0 oz - Black (Patent) Malt (500.0 SRM) (Grain)",
        "4.0 oz - Black Barley (Stout) (456.9 SRM) (Grain)",
        "1 lbs - Dark Dry Extract (17.5 SRM) (Grain)",
        "6 lbs - Brewferm Dark Malt Extract (22.8 SRM) (Grain)",
        "1.0 oz - Cluster [7.0%] - Boil 60 min (Hops)",
        "1.0 oz - Goldings, East Kent [5.0%] - Boil 25 min (Hops)",
        "1.00 tsp - Irish Moss (Boil 15 min) (Misc)",
        "1 pkgs - Irish Ale Yeast (White Labs #WLP004) (Yeast)",
        "3.00 - Vanilla (Secondary 7 days) (Misc)"
    ],
    "name": "None More Black Vanilla Stout",
    "name_raw": "None More Black Vanilla Stout",
    "rating": "4.5",
    "source": "beerrecipes.com",
    "style": "Sweet Stout",
    "style_raw": "Sweet Stout",
    "votes": "2"
}