{
    "bjcp": "16C",
    "id": "9036",
    "ingredients": [
        "8.0 oz - Aromatic Malt (26.0 SRM) (Grain)",
        "4.0 oz - Caraaroma (130.0 SRM) (Grain)",
        "4.0 oz - Carafa III (525.0 SRM) (Grain)",
        "6 lbs - Pilsner Liquid Extract (3.5 SRM) (Grain)",
        "1 lbs - Candi Sugar, Amber (90.0 SRM) (Grain)",
        "1 lbs - Corn Sugar (Dextrose) (0.0 SRM) (Grain)",
        "1.0 oz - Magnum [14.0%] - Boil 60 min (Hops)",
        "1 lbs - Light Dry Extract [Boil for 15 min] (8.0 SRM) (Grain)"
    ],
    "name": "Saison de Noel",
    "name_raw": "Saison de Noel",
    "rating": 2,
    "source": "beerrecipes.com",
    "style": "Saison",
    "style_raw": "Saison",
    "votes": 0
}