{
    "bjcp": "10A",
    "id": "1066",
    "ingredients": [
        "3 Gallons Bottled Spring Water",
        "22 oz can West Coast Pale ale Hopped Malt Extract",
        "22 oz can Mr Beer Pale Malt Extract",
        "1.75 lb Light Malt Extract",
        "1 oz Cascade pellets 60 minutes in boil",
        "1/4 oz Cascade pellets last 30 minutes in boil",
        "1/4 oz Cascade pellets last 10 minutes in boil",
        "1 tsp Spanish Sea Salt",
        "Wyeast American Liquid Ale Yeast # 1056",
        "1/2 cup table sugar"
    ],
    "name": "Sticky Nevada Pale Ale",
    "name_raw": "Sticky Nevada Pale Ale",
    "rating": "4.0",
    "source": "beerrecipes.com",
    "style": "American Pale Ale",
    "style_raw": "American Pale Ale",
    "votes": "3"
}