{
    "bjcp": "13F",
    "id": "496",
    "ingredients": [
        "4# English Pale Ale malt",
        ".5# carapils malt",
        "6 oz English Roasted Barley",
        "6 oz English Black Roast",
        "4 oz Flaked Barley",
        "4 oz Flaked Wheat (considering using spelt)",
        "4 oz English Chocolate malt",
        "2 oz English Smoked (HB) (I'm considering leaving this out, may be making"
    ],
    "name": "Bees and Bears RIS",
    "name_raw": "Bees and Bears RIS",
    "rating": "1.9",
    "source": "beerrecipes.com",
    "style": "Russian Imperial Stout",
    "style_raw": "Russian Imperial Stout",
    "votes": "7"
}