{
    "bjcp": "21B",
    "id": "1405",
    "ingredients": [
        "12 lbs American 2 Row",
        "8 oz Caramel/Crystal 60L",
        "8 oz Special B",
        "6 oz Roasted Barley",
        "1 tsp Fresh Ginger 10 min",
        "1 tsp Ground Nutmeg 10 min",
        "1 Cinnamon Stick 10 min",
        "1 Cinnamon Stick 5 min",
        "1.5 oz Kent Goldings (5.7% AAU) 60 min",
        ".5 oz Kent Goldings (5.7% AAU) 2 min",
        "Wyeast - American Ale #1056 or White Labs California Ale",
        "**Recommend you do a yeast starter 24-48 hours before brew day"
    ],
    "name": "Season's Greetings Winter Ale",
    "name_raw": "Season's Greetings Winter Ale",
    "rating": "4.0",
    "source": "beerrecipes.com",
    "style": "Christmas/Winter Specialty Spiced Beer",
    "style_raw": "Christmas/Winter Specialty Spiced Beer",
    "votes": "2"
}