{
    "bjcp": "18A",
    "id": "2196",
    "ingredients": [
        "11.00 g - PH 5.2 Stabilizer (Mash 60 min) (Misc)",
        "11 lbs 0.4 oz - Pilsner (Weyermann) (1.7 SRM) (Grain)",
        "15.9 oz - Munich II (Weyermann) (8.5 SRM) (Grain)",
        "5.3 oz - Caraamber (Weyermann) (36.0 SRM) (Grain)",
        "3.5 oz - Melanoidin (Weyermann) (30.0 SRM) (Grain)",
        "8.8 oz - Brown Sugar, Light (8.0 SRM) (Grain)",
        "1.3 oz - Styrian Goldings [5.4%] - Boil 60 min (Hops)",
        "1.00 - Whirlfloc Tablet (Boil 10 min) (Misc)",
        "0.4 oz - Motueka [7.0%] - Boil 10 min (Hops)",
        "0.4 oz - Motueka [7.0%] - Steep 0 min (Hops)",
        "1 pkgs - Belgian Abbey II (Wyeast Labs #1762) (Yeast)"
    ],
    "name": "B-Side Belgium Blonde",
    "name_raw": "B-Side Belgium Blonde",
    "rating": 2,
    "source": "beerrecipes.com",
    "style": "Belgian Blond Ale",
    "style_raw": "Belgian Blond Ale",
    "votes": 0
}