{
    "bjcp": "12B",
    "id": "9423",
    "ingredients": [
        "0.50 oz - Burton Water Salts (Mash 60 min) (Misc)",
        "1 lbs - Chocolate Wheat Malt (400.0 SRM) (Grain)",
        "1 lbs - Honey Malt (Gambrinus) (25.0 SRM) (Grain)",
        "1 lbs - Pale Malt, Maris Otter (3.0 SRM) (Grain)",
        "14.4 oz - Carafa II (412.0 SRM) (Grain)",
        "13.8 oz - Chocolate 6-Row (Briess) (350.0 SRM) (Grain)",
        "13.6 oz - Oats, Flaked (1.0 SRM) (Grain)",
        "3.5 oz - Borlander Munich Malt (Briess) (10.0 SRM) (Grain)",
        "1.0 oz - Cascade [5.5%] - Boil 60 min (Hops)",
        "3 lbs - DME Golden Light (Briess) [Boil for 30 min] (4.0 SRM) (Grain)",
        "3 lbs 4.8 oz - LME Porter (Briess) [Boil for 20 min] (135.0 SRM) (Grain)",
        "2.0 oz - Cascade [5.5%] - Boil 10 min (Hops)",
        "3.00 oz - Decaf Espresso Beans (Boil 5 min) (Misc)",
        "1.00 oz - Unsweetened Chocolate Powder (Boil 5 min) (Misc)",
        "1 pkgs - Nottingham (Danstar #-) (Yeast)"
    ],
    "name": "Kitchen Sink Dark",
    "name_raw": "Kitchen Sink Dark",
    "rating": "4.0",
    "source": "beerrecipes.com",
    "style": "Robust Porter",
    "style_raw": "Robust Porter",
    "votes": "1"
}