{
    "bjcp": "10C",
    "id": "13772",
    "ingredients": [
        "18 lbs - Pale Malt (2 Row) US (2.0 SRM) (Grain)",
        "2 lbs - Caramel Malt - 60L 6-Row (Briess) (60.0 SRM) (Grain)",
        "1 lbs - Chocolate Malt (350.0 SRM) (Grain)",
        "1 lbs - Special B Malt (180.0 SRM) (Grain)",
        "1.5 oz - Galena [12.5%] - Boil 90 min (Hops)",
        "0.50 tsp - Irish Moss (Boil 10 min) (Misc)",
        "1.5 oz - Fuggle [4.5%] - Boil 3 min (Hops)",
        "1 pkgs - American Ale II (Wyeast Labs #1272) (Yeast)"
    ],
    "name": "Brown Ale AG",
    "name_raw": "Brown Ale AG",
    "rating": 2,
    "source": "beerrecipes.com",
    "style": "American Brown Ale",
    "style_raw": "American Brown Ale",
    "votes": 0
}