{
    "bjcp": "10B",
    "id": "1474",
    "ingredients": [
        "2 lbs Oats (mash/sparge) - mash with amylase",
        "1 lb Belgian Candi Sugar (mash) - see 'Brewing notes'",
        "3 lbs White Sorghum Syrup (prior to boil)",
        "3 lbs Brown Rice Syrup (prior to boil)",
        "1 lb Corn Syrup (prior to boil)",
        "2 lbs Corn Sugar - Dextrose (prior to boil)",
        "0.5 oz Columbus Hops - Leaf (60 min)",
        "1 tsp Allspice (40 min)",
        "1 tsp Cinnamon (40 min)",
        "0.5 oz Cascade Hops - Leaf (30 min)",
        "1 tbsp Orange Zest (20 min)",
        "0.5 oz Columbus Hops - Leaf (10 min)",
        "0.5 oz Fuggles Hops - Leaf (5 min)",
        "1 pkg Safbrew T-58 Dry Yeast",
        "Secondary:",
        "1 oz Orange Zest",
        "1 oz Cloves",
        "Brewing notes:The &amp;quot;Belgian Candi Sugar&amp;quot; is actually (approximately) 2 pounds of Sweet Potatoes that have been run through a food processor, and used as a mash in 1 gallon of 165 degree water for one hour. Amylase to be added to the sweet potato mash in order to facilitate breaking down the starches. After it's been &amp;quot;mashed&amp;quot;, the mixture will be pureed with a stick blender, then boiled down to a syrup and dumped into the wort as it's being brought up to a boil."
    ],
    "name": "American Amber Ale",
    "name_raw": "American Amber Ale",
    "rating": "3.7",
    "source": "beerrecipes.com",
    "style": "American Amber Ale",
    "style_raw": "American Amber Ale",
    "votes": "19"
}