{
    "bjcp": "14B",
    "id": "8878",
    "ingredients": [
        "7.93 gal - Distilled Water (Water)",
        "10.04 g - Gypsum (Calcium Sulfate) (Mash 60 min) (Misc)",
        "3.00 g - Epsom Salt (MgSO4) (Mash 60 min) (Misc)",
        "11 lbs 0.4 oz - Lager Malt (1.5 SRM) (Grain)",
        "14.1 oz - Caramunich II (Weyermann) (63.0 SRM) (Grain)",
        "3.5 oz - Cara-Pils/Dextrine (2.0 SRM) (Grain)",
        "8.8 oz - Corn Sugar (Dextrose) (0.0 SRM) (Grain)",
        "0.7 oz - Columbus (Tomahawk) [14.0%] - Boil 60 min (Hops)",
        "2.1 oz - Cascade [5.5%] - Boil 15 min (Hops)",
        "5.00 g - Irish Moss (Boil 10 min) (Misc)",
        "1.4 oz - Columbus (Tomahawk) [14.0%] - Boil 7 min (Hops)",
        "1.8 oz - Cascade [5.5%] - Steep 30 min (Hops)",
        "1 pkgs - American Ale (Wyeast Labs #1056) (Yeast)",
        "1.4 oz - Centennial [10.0%] - Dry Hop 7 days (Hops)"
    ],
    "name": "Bottoms Up!",
    "name_raw": "Bottoms Up!",
    "rating": "4.0",
    "source": "beerrecipes.com",
    "style": "American IPA",
    "style_raw": "American IPA",
    "votes": "1"
}