{
    "bjcp": "7B",
    "id": "1901",
    "ingredients": [
        "3.00 g - Gypsum (Calcium Sulfate) (Mash 60 min) (Misc)",
        "7 lbs - Pale Malt - 2 Row (Schreier) (2.0 SRM) (Grain)",
        "1 lbs 8.0 oz - Vienna (Hoepfner) (4.0 SRM) (Grain)",
        "1 lbs - Brewers Malt 6-Row (Briess) (1.8 SRM) (Grain)",
        "8.0 oz - Caramel/Crystal Malt - 40L (40.0 SRM) (Grain)",
        "8.0 oz - Caramel/Crystal Malt - 60L (60.0 SRM) (Grain)",
        "2.0 oz - Carafa Special II (Weyermann) (415.0 SRM) (Grain)",
        "1.0 oz - Northern Brewer [8.6%] - Boil 60 min (Hops)",
        "0.25 tsp - Irish Moss (Boil 10 min) (Misc)",
        "1.0 oz - Northern Brewer [8.6%] - Boil 10 min (Hops)",
        "0.5 oz - Northern Brewer [8.6%] - Steep 15 min (Hops)",
        "1 pkgs - California Lager (Wyeast Labs #2112) (Yeast)"
    ],
    "name": "Cleveland Steam v1.3",
    "name_raw": "Cleveland Steam v1.3",
    "rating": "4.0",
    "source": "beerrecipes.com",
    "style": "California Common Beer",
    "style_raw": "California Common Beer",
    "votes": "1"
}