{
    "bjcp": "22A",
    "id": "275",
    "ingredients": [
        "7 pounds, light dry extract",
        "1-1/2 teaspoons, liquid smoke",
        "1-1/2 ounces, Tettnanger hops (boil)",
        "1 ounce, Tettnanger hops (finish)",
        "1/2 teaspoon, Irish moss",
        "2 packs, Red Star lager yeast"
    ],
    "name": "Rauchbier",
    "name_raw": "Rauchbier",
    "rating": "3.8",
    "source": "beerrecipes.com",
    "style": "Classic Rauchbier",
    "style_raw": "Classic Rauchbier",
    "votes": "6"
}