{
    "bjcp": "1B",
    "id": "50",
    "ingredients": [
        "3 lbs 5 oz Munton & Fison American Light Malt Syrup (boil 60 mins)",
        "1 lb Munton & Fison Light Dried Malt Extract (boil 60 mins)",
        "1 oz Willamette Pellets (3.9% Alpha) (boil 45 mins)",
        "1/2 oz Cascade Pellets (5.6% Alpha) (boil 5 mins)",
        "1.75 oz WYeast #2035 American Lager",
        "1 teaspoon Irish Moss (boil 10 mins)",
        "4 oz Malto Dextrin (boil 30 mins)(note: I have no idea why I used"
    ],
    "name": "Bulwark American Lager",
    "name_raw": "Bulwark American Lager",
    "rating": "3.0",
    "source": "beerrecipes.com",
    "style": "Standard American Lager",
    "style_raw": "Standard American Lager",
    "votes": "12"
}