{
    "bjcp": "21A",
    "id": "542",
    "ingredients": [
        "7# Alexander's Pale extract",
        "1# Dextrin malt",
        "1# Vienna (presumably Briess)",
        "1/4 oz Kent Golding & 1/4 oz. Clusters after 5 min.",
        "1/4 oz KG & 1/4 oz. Clusters after 20 & 40 min.",
        "1/2 oz. Mt Hood after 58 min.",
        "2 tsp. gypsum in 60 min. boil",
        "2 whole, roasted Hatch Chiis & 2 oz. chopped New Mexico chilis"
    ],
    "name": "Green Chili Beerito",
    "name_raw": "Green Chili Beerito",
    "rating": "5.0",
    "source": "beerrecipes.com",
    "style": "Spice, Herb, or Vegetable Beer",
    "style_raw": "Spice, Herb, or Vegetable Beer",
    "votes": "1"
}