{
    "bjcp": "14B",
    "id": "13803",
    "ingredients": [
        "&bull;\t1.7 Kg Black Rock Amber Malt Extract",
        "&bull;\t1 Kg Briess Pilsen Light DME",
        "&bull;\t230 g Crystal Malt (Pale)",
        "&bull;\t37.5 AAU&rsquo;s of Chinook Hops",
        "&bull;\t12.3 AAU&rsquo;s of Golding Hops",
        "&bull;\t10 g Mangrove Jack's British Ale Yeast",
        "&bull;\t24 Litres of Clean water"
    ],
    "name": "Jacked up",
    "name_raw": "Jacked up",
    "rating": 2,
    "source": "beerrecipes.com",
    "style": "American IPA",
    "style_raw": "American IPA",
    "votes": 0
}