{
    "bjcp": "14B",
    "id": "1064",
    "ingredients": [
        "2tsp gypsum",
        "1# crystal rye malt",
        "6# light LME",
        "2# amber DME",
        "3oz cascade bittering pellets",
        "1oz fuggles flavoring pellets",
        "1oz cascade aroma pellets",
        "1oz columbus pellets for dry hoppiing",
        "1/2# light brown sugar",
        "1tsp irish moss",
        "wyeast 1056"
    ],
    "name": "Foggy Goggle Rye IPA",
    "name_raw": "Foggy Goggle Rye IPA",
    "rating": "4.5",
    "source": "beerrecipes.com",
    "style": "American IPA",
    "style_raw": "American IPA",
    "votes": "18"
}