{
    "bjcp": "13C",
    "id": "417",
    "ingredients": [
        "6# unhopped dark malt extract",
        "1# unhopped dry malt",
        "8 oz chocolate malt",
        "6 oz roasted barley",
        "4 oz black patent malt",
        "8 oz rolled oats",
        "1 tbs CaCO3",
        "2 oz Northern Brewer - 8.2 AAU",
        "2 oz Fuggles - 4.2 AAU",
        "Irish Moss - 30 min",
        "Liquid Irish Ale yeast"
    ],
    "name": "First Oatmeal Stout",
    "name_raw": "First Oatmeal Stout",
    "rating": "3.9",
    "source": "beerrecipes.com",
    "style": "Oatmeal Stout",
    "style_raw": "Oatmeal Stout",
    "votes": "14"
}