{
    "bjcp": "12B",
    "id": "977",
    "ingredients": [
        "6 lb. Amber Extract Syrup",
        "0.88 lb. Medium Crystal",
        "0.75 lb. Flaked Barley",
        "0.5 lb. Aromatic Malt",
        "0.5 lb. Chocolate Malt",
        "0.5 lb. Special B Malt",
        "0.25 lb. Black Patent Malt",
        "2.75 oz. Willamette\t@30 minutes into boil",
        "0.25 oz. Centennial\t@10 minutes into boil",
        "Wyeast 1056 American Ale",
        "5 Vanilla Beans"
    ],
    "name": "Porter In Her Place",
    "name_raw": "Porter In Her Place",
    "rating": "4.0",
    "source": "beerrecipes.com",
    "style": "Robust Porter",
    "style_raw": "Robust Porter",
    "votes": "1"
}