{
    "bjcp": "10A",
    "id": "1491",
    "ingredients": [
        "10 lbs Malted Red Millet, cracked (mash/sparge)",
        "1 lb Flaked Corn (mash/sparge)",
        "1 oz Magnum Hops (60 min)",
        "0.75 Perle Hops (60 min)",
        "3 lbs Sorghum Syrup (30 min)",
        "1 Whirlfloc tablet (30 min)",
        "1 oz Willamette Hops (15 min)",
        "1 oz Willamette Hops (flameout)",
        "1 pkg Nottingham Ale Yeast",
        "Dry Hopping:",
        "1 oz Cascade Hops, whole leaf"
    ],
    "name": "Red Millet Pale Ale",
    "name_raw": "Red Millet Pale Ale",
    "rating": "4.0",
    "source": "beerrecipes.com",
    "style": "American Pale Ale",
    "style_raw": "American Pale Ale",
    "votes": "1"
}