{
    "bjcp": "13F",
    "id": "312",
    "ingredients": [
        "1 pound, crushed crystal malt",
        "1 pound, crushed roasted barley",
        "1-1/2 pounds, crushed black patent malt",
        "9 pounds, Munton & Fison dark dry malt extract",
        "1 can, John Bull dark hopped malt extract",
        "2 inches, brewers licorice",
        "2 ounces, Nugget leaf hops",
        "2 ounces, Galena leaf hops",
        "1 ounce, Cascade hops",
        "2 packs, Doric ale yeast",
        "1 ounce, amylase enzyme"
    ],
    "name": "Crankcase Stout",
    "name_raw": "Crankcase Stout",
    "rating": "3.7",
    "source": "beerrecipes.com",
    "style": "Russian Imperial Stout",
    "style_raw": "Russian Imperial Stout",
    "votes": "12"
}