{
    "bjcp": "12A",
    "id": "322",
    "ingredients": [
        "8 pounds, American 6-row (Klages) malt",
        "1 pound, Munich malt",
        "1/2 pound, crystal malt (90L)",
        "1/2 pound, black patent malt",
        "1/2 pound, chocolate malt",
        "1/2 pound, roasted barley",
        "1 teaspoon, calcium carbonate",
        "1 ounce, Northern Brewer hops (boil)",
        "1/2 ounce, Cascade hops (boil)",
        "1/2 ounce, Cascade hops (finish)",
        "Whitbread ale yeast"
    ],
    "name": "All Grain Porter",
    "name_raw": "All Grain Porter",
    "rating": "2.9",
    "source": "beerrecipes.com",
    "style": "Brown Porter",
    "style_raw": "Brown Porter",
    "votes": "11"
}