{
    "bjcp": "2B",
    "id": "1772",
    "ingredients": [
        "1 lbs - Caramel/Crystal Malt - 20L (20.0 SRM) (Grain)",
        "6 lbs - Light Dry Extract (8.0 SRM) (Grain)",
        "2 lbs - Extra Light Dry Extract (3.0 SRM) (Grain)",
        "1.0 oz - Cluster [7.0%] - Boil 45 min (Hops)",
        "1.0 oz - Hallertauer Hersbrucker [4.0%] - Boil 45 min (Hops)",
        "1.00 lbs - Honey (Boil 45 min) (Misc)",
        "1.00 tsp - Irish Moss (Boil 15 min) (Misc)",
        "1.0 oz - Hallertauer Hersbrucker [4.0%] - Boil 5 min (Hops)",
        "1 pkgs - Bohemian Lager (Wyeast Labs #2124) (Yeast)"
    ],
    "name": "Magic Carpet Pilsner",
    "name_raw": "Magic Carpet Pilsner",
    "rating": 2,
    "source": "beerrecipes.com",
    "style": "Bohemian Pilsener",
    "style_raw": "Bohemian Pilsener",
    "votes": 0
}